Workbook

Sheet Synthèse
C1: =_xlfn.CONCAT(D3, " / ",D4, " ",D5) -> Kangourou / Toto Tutu | L1: Synthèse qualification | O1: Colonnes techniques, ne pas imprimer après M
C3: Totem | D3: Kangourou | G3: Cours | H3: RU - Chef de camp JS SdC/T
C4: Prénom | D4: Toto | G4: N° | H4: PBS CH NE 221-26
C5: Nom | D5: Tutu | G5: Date | H5: Mercredi 8 avril 2026
C7: Commentaire général de la maîtrise
C12: Récapitulatif points positifs | H12: Récapitulatif points à améliorer
C17: Critère de réussite du cours | E17: Toutes les sphères minimum à 80%
C19: Sphère | E19: Moyenne | G19: Report du commentaire global de la sphère
C21: Posture | G21: =Posture!C4 -> 0
O23: Min
C24: Réussite du cours | F24: =IF(AND(COUNTIF(F26:F42, "=Réussi") >= 3, F47="AUCUN"),"Réussi","Echoué") -> Réussi | O24: 3
C26: ='A - Techniques JS'!C1 -> A - Techniques JS | E26: ='A - Techniques JS'!C3 | F26: =IF(E26 >= O26, "Réussi", "Echoué") -> Réussi | G26: =IF(ISBLANK('A - Techniques JS'!E4),"",'A - Techniques JS'!E4) | O26: 0.8
D27: 1. Planification randonnée | E27: {=IFERROR(INDIRECT("'" & $C$26 & "'!" & $O27)+M27,"")} | G27: {=INDIRECT("'" & $C$26 & "'!" & $P27)} -> 0 | N27: =MATCH(LEFT(D27,2)&"*",'A - Techniques JS'!C:C,0) -> 11 | O27: =_xlfn.CONCAT("J",$N27) -> J11 | P27: =_xlfn.CONCAT("K",$N27) -> K11
D28: 2. Réalisation randonnée | E28: {=IFERROR(INDIRECT("'" & $C$26 & "'!" & $O28)+M28,"")} | G28: {=INDIRECT("'" & $C$26 & "'!" & $P28)} -> 0 | N28: =MATCH(LEFT(D28,2)&"*",'A - Techniques JS'!C:C,0) -> 35 | O28: =_xlfn.CONCAT("J",$N28) -> J35 | P28: =_xlfn.CONCAT("K",$N28) -> K35
D29: 3. Correction randonnée | E29: {=IFERROR(INDIRECT("'" & $C$26 & "'!" & $O29)+M29,"")} | G29: {=INDIRECT("'" & $C$26 & "'!" & $P29)} -> 0 | N29: =MATCH(LEFT(D29,2)&"*",'A - Techniques JS'!C:C,0) -> 46 | O29: =_xlfn.CONCAT("J",$N29) -> J46 | P29: =_xlfn.CONCAT("K",$N29) -> K46
D30: 4. Planifier activité d'ampleur | E30: {=IFERROR(INDIRECT("'" & $C$26 & "'!" & $O30)+M30,"")} | G30: {=INDIRECT("'" & $C$26 & "'!" & $P30)} -> 0 | N30: =MATCH(LEFT(D30,2)&"*",'A - Techniques JS'!C:C,0) -> 68 | O30: =_xlfn.CONCAT("J",$N30) -> J68 | P30: =_xlfn.CONCAT("K",$N30) -> K68
D31: 5. Animer sport de camp | E31: {=IFERROR(INDIRECT("'" & $C$26 & "'!" & $O31)+M31,"")} | G31: {=INDIRECT("'" & $C$26 & "'!" & $P31)} -> 0 | N31: =MATCH(LEFT(D31,2)&"*",'A - Techniques JS'!C:C,0) -> 92 | O31: =_xlfn.CONCAT("J",$N31) -> J92 | P31: =_xlfn.CONCAT("K",$N31) -> K92
D32: 6. Correction SC | E32: {=IFERROR(INDIRECT("'" & $C$26 & "'!" & $O32)+M32,"")} | G32: {=INDIRECT("'" & $C$26 & "'!" & $P32)} -> 0 | N32: =MATCH(LEFT(D32,2)&"*",'A - Techniques JS'!C:C,0) -> 107 | O32: =_xlfn.CONCAT("J",$N32) -> J107 | P32: =_xlfn.CONCAT("K",$N32) -> K107
D33: 7. Correction AC | E33: {=IFERROR(INDIRECT("'" & $C$26 & "'!" & $O33)+M33,"")} | G33: {=INDIRECT("'" & $C$26 & "'!" & $P33)} -> 0 | N33: =MATCH(LEFT(D33,2)&"*",'A - Techniques JS'!C:C,0) -> 121 | O33: =_xlfn.CONCAT("J",$N33) -> J121 | P33: =_xlfn.CONCAT("K",$N33) -> K121
C35: ='B - Organisation'!C1 -> B - Organisation | E35: ='B - Organisation'!C3 | F35: =IF(E35 >= O35, "Réussi", "Echoué") -> Réussi | G35: =IF(ISBLANK('B - Organisation'!E4),"",'B - Organisation'!E4) | O35: 0.8
D36: 1. Programme de camp | E36: {=IFERROR(INDIRECT("'" & $C$35 & "'!" & $O36)+M36,"")} | G36: {=INDIRECT("'" & $C$35 & "'!" & $P36)} -> 0 | N36: =MATCH(LEFT(D36,2)&"*",'B - Organisation'!C:C,0) -> 11 | O36: =_xlfn.CONCAT("J",$N36) -> J11 | P36: =_xlfn.CONCAT("K",$N36) -> K11
D37: 2. Administration du camp | E37: {=IFERROR(INDIRECT("'" & $C$35 & "'!" & $O37)+M37,"")} | G37: {=INDIRECT("'" & $C$35 & "'!" & $P37)} -> 0 | N37: =MATCH(LEFT(D37,2)&"*",'B - Organisation'!C:C,0) -> 23 | O37: =_xlfn.CONCAT("J",$N37) -> J23 | P37: =_xlfn.CONCAT("K",$N37) -> K23
D38: 3. Concept de sécurité | E38: {=IFERROR(INDIRECT("'" & $C$35 & "'!" & $O38)+M38,"")} | G38: {=INDIRECT("'" & $C$35 & "'!" & $P38)} -> 0 | N38: =MATCH(LEFT(D38,2)&"*",'B - Organisation'!C:C,0) -> 52 | O38: =_xlfn.CONCAT("J",$N38) -> J52 | P38: =_xlfn.CONCAT("K",$N38) -> K52
D39: 4. Réunions | E39: {=IFERROR(INDIRECT("'" & $C$35 & "'!" & $O39)+M39,"")} | N39: 81 | O39: =_xlfn.CONCAT("J",$N39) -> J81 | P39: =_xlfn.CONCAT("K",$N39) -> K81
D40: 4. Organisation maîtrises | E40: {=IFERROR(INDIRECT("'" & $C$35 & "'!" & $O40)+M40,"")} | G40: {=INDIRECT("'" & $C$35 & "'!" & $P40)} -> 0 | N40: 101 | O40: =_xlfn.CONCAT("J",$N40) -> J101 | P40: =_xlfn.CONCAT("K",$N40) -> K101
C42: ='C - Scoutisme'!C1 -> C - Scoutisme | E42: ='C - Scoutisme'!C3 | F42: =IF(E42 >= O42, "Réussi", "Echoué") -> Réussi | G42: =IF(ISBLANK('C - Scoutisme'!E4),"",'C - Scoutisme'!E4) | O42: 0.8
D43: 1. Activité de grande ampleur | E43: {=IFERROR(INDIRECT("'" & $C$42 & "'!" & $O43)+M43,"")} | G43: {=INDIRECT("'" & $C$42 & "'!" & $P43)} -> 0 | N43: =MATCH(LEFT(D43,2)&"*",'C - Scoutisme'!C:C,0) -> 11 | O43: =_xlfn.CONCAT("J",$N43) -> J11 | P43: =_xlfn.CONCAT("K",$N43) -> K11
D44: 2. Programme de camp | E44: {=IFERROR(INDIRECT("'" & $C$42 & "'!" & $O44)+M44,"")} | G44: {=INDIRECT("'" & $C$42 & "'!" & $P44)} -> 0 | N44: =MATCH(LEFT(D44,2)&"*",'C - Scoutisme'!C:C,0) -> 20 | O44: =_xlfn.CONCAT("J",$N44) -> J20 | P44: =_xlfn.CONCAT("K",$N44) -> K20
D45: 3. Programme annuel | E45: {=IFERROR(INDIRECT("'" & $C$42 & "'!" & $O45)+M45,"")} | G45: {=INDIRECT("'" & $C$42 & "'!" & $P45)} -> 0 | N45: =MATCH(LEFT(D45,2)&"*",'C - Scoutisme'!C:C,0) -> 43 | O45: =_xlfn.CONCAT("J",$N45) -> J43 | P45: =_xlfn.CONCAT("K",$N45) -> K43
C47: Critère éliminatoire | F47: =IF(COUNTIF('Critères éliminatoires'!D9:D26, "OUI")>0, "OUI", "AUCUN") -> AUCUN
C48: ='Critères éliminatoires'!C4 -> 0
C50: Joker | F50: AUCUN
C51: En cas de besoin, la maîtrise dispose d'un Joker qu'elle peut invoquer pour modifier la note d'une sphère, d'un demi point. Par exemple, si elle juge que le participant peut obtenir sa licence alors que la qualification non. Il est possible d'utiliser le joker une seule fois, si la maîtrise choisit de l'utiliser, elle doit détailler pour quelles raisons, et indiquer pour quelle sphère. | F51: Ou :
F52: Justificatif

Sheet Posture
C1: Posture du chef de camp SdC/T | G1: =_xlfn.CONCAT(Synthèse!C1, " / Cours ", Synthèse!H3) -> Kangourou / Toto Tutu / Cours RU - Chef de camp JS SdC/T
C3: Commentaire général | G3: Sera reporté dans la Synthèse
C7: A. Collaboration - Maîtrise/Humain | E7: Commentaire | G7: Quand | I7: Énergie globale
C8: A1. Collabore efficacement avec les autres
C9: A2. Critique de manière constructive
C10: A3. Cherche des relations collégiales dans chaque situation
C11: A4. Instaure une dynamique harmonieuse et respectueuse de chacun.e
C12: A5. Identifie les dynamiques internes et réagit en conséquence
C14: B. Collaboration - Objectif commun | E14: Commentaire | G14: Quand
C15: B1. Contribue à l'atteinte des buts et objectifs (idées, critiques, améliorations, solutions adéquates, etc.)
C16: B2. Identifie les compétences et caractères de chaque membre de son équipe et crée une dynamique de travail efficace
C17: B3. Agit de manière autonome
C18: B4. Endosse le rôle adéquat en vue d'atteindre les objectifs fixés
C19: B5. Utilise son savoir et ses connaissances de manière utile et adéquate (partage, aide, etc.)
C21: C. Environnement - Vision d'ensemble | E21: Commentaire | G21: Quand
C22: C1. Contribue/veille au bien-être général
C23: C2. Anticipe les besoins globaux et personnels
C25: D. Adaptation - Réaction au stress | E25: Commentaire | G25: Quand | I25: Énergie individuelle
C26: D1. Garde la tête froide en situation de stress (calme, ton adéquat, autonomie, etc.)
C27: D2. Réagit de manière adaptée dans une situation de stress
C28: D3. Garde une vision globale en tout temps
C30: E. Engagement personnel - Proactivité | E30: Commentaire | G30: Quand
C31: E1. S'affirme dans un groupe de manière adaptée
C32: E2. Fait preuve d'initiative et d'investissement
C33: E3. Montre de l'intérêt en toute situation ( = respect)
C34: E4. A du feeling avec les participant.e.s (et les formateurices)
C35: E5. Utilise son savoir et ses connaissances (partage)
C36: E6. Agit de manière proactive
C38: F. Comportement - Communication | E38: Commentaire | G38: Quand | I38: Comportement du/de la participant.e
C39: F1. Parle avec assurance
C40: F2. S'exprime de manière intelligible
C41: F3. Adapte son discours à la situation/personne
C42: F4. Adapte sa posture/gestuelle à la situation (écoute active, CNV)
C44: G. Comportement - Actions | E44: Commentaire | G44: Quand
C45: G1. Agit avec assurance
C46: G2. Agit en leader
C47: G3. Agit de manière autonome
C48: G4. Agit de manière responsable et réfléchie
C49: G5. Est fidèle, serviable, rigoureux, discipliné, franc, etc.
C51: H. Comportement - Attitude | E51: Commentaire | G51: Quand
C52: H1. Montre la volonté de réussir le cours
C53: H2. Renvoie une image d'exemple pour les jeunes/responsables
C54: H3. Renvoie l'image d'une personne de confiance et garante de la sécurité
C55: H4. Pense de manière autonome
C56: H5. A une attitude responsable et réfléchie
C57: H6. S'investit pour s'améliorer
C58: H7. Critique de manière constructive
C59: H8. Se remet en question suite à la critique ou de lui/elle-même
C60: H9. Prend du recul suite à la critique
C61: H10. Fait preuve d'ouverture d'esprit et de tolérance
C62: H11. Apporte de la motivation
C64: I. Personnalité - Estime de soi | E64: Commentaire | G64: Quand | I64: Personnalité du/de la participant.e
C65: I1. Evalue sa progression personnelle
C66: I2. Formule des objectifs personnels pertinents
C67: I3. S'auto-évalue de manière adéquate
C69: J. Personnalité - Forces et limites | E69: Commentaire | G69: Quand
C70: J1. Identifie/exprime ses forces et ses limites
C74: Questions pour répartir les observations :
C78: 1. Se focalise sur le participant.e ?
C79: 1.A. Si oui : concerne le comportement ou la personnalité du participant.e ?
C80: Comportement : choisir une catégorie parmi Communication, Actions ou Attitudes [F,G,H]
C81: Personnalité : choisir une catégorie parmi Estime de soi ou Forces-limites [I,J]
C83: 1.B. Si non : la dynamique est-elle plutôt globale ou individuelle ?
C84: Globale : est-ce une situation de collaboration ou de vision d'ensemble ?
C85: Collaboration : choisir une catégorie parmi Axé maîtrise-humain ou Axé objectif commun [A,B]
C86: Vision d'ensemble : l'observation est liée à l'atmosphère, à la situation [C]
C87: Individuelle : choisir une catégorie parmi Adaptation au stress ou Proactivité [D,E]

Sheet A - Techniques JS
C1: A - Techniques JS | K1: =_xlfn.CONCAT(Synthèse!C1, " // Cours ", Synthèse!H3) -> Kangourou / Toto Tutu // Cours RU - Chef de camp JS SdC/T | N1: Colonnes d'informations supplémentaires
N2: =COUNTBLANK(E11:E164) -> 55 | O2: =COUNTBLANK(H11:H164)-N2 -> 99 | P2: Nombre d'indicateurs vides
C3: =O6 | E3: Commentaire général | K3: Sera reporté dans la Synthèse | O3: =AVERAGEIF(H11:H164,"<>0") -> #DIV/0! | P3: Moyenne des indicateurs (tous confondus, sans passer par les pondérations)
O4: {=IFERROR(SUMPRODUCT(N11:N164,F11:F164)/SUMPRODUCT(--(N11:N164<>""),F11:F164),"")} | P4: Note de spère sans arrondi
O5: =C3-O4 -> #VALUE! | P5: Delta entre note sphèe arrondie et sans arrondi
F6: Pond. Obj. | G6: Pondérations | H6: Final | I6: Moy critères | J6: Moy objectif | O6: =IFERROR(ROUND(IF(O4<=3, (O4-1)/2, 1 + (O4-3)*0.25),2),"") | P6: Note de la sphère en % (3 = 100)
C7: Objectifs
D8: Critère | N8: objectif
E9: Indicateur | K9: Commentaire | N9: sans arrondi | O9: delta entre objectif arrondi et non arrondi
C11: 1. Planifier une randonnée pour la branche éclais | F11: 2 | J11: =IFERROR(ROUND(IF(N11<=3, (N11-1)/2, 1 + (N11-3)*0.25),2),"") | N11: {=IFERROR(SUMPRODUCT(I12:I34,G12:G34)/SUMPRODUCT(--(I12:I34<>""),G12:G34),"")} | O11: =J11-N11 -> #VALUE!
D12: 1. Un tracé de randonnée adapté est conçu | G12: 1 | I12: =IFERROR(AVERAGEIF(H13:H17, "<>0"), "")
E13: Le tracé est lisible (contraste, les informations sont lisibles, on arrive à lire la carte sous les indications)
E14: L'itinéraire est adapté aux participant.e.s (itensité, difficulté)
E15: L'itinéraire évite les dangers, si impossible ces derniers sont clairement identifiés
E16: Les points de passage sont indiqués clairement et numérotés
E17: Des points de non-retour et échappatoires sont prévus lorsque nécessaire
D18: 2. Un dispositif de marche de randonnée est réalisé | G18: 1 | I18: =IFERROR(AVERAGEIF(H19:H25, "<>0"), "")
E19: Le canevas du dispositif de marche et rempli correctement (responsable, n° de carte, date)
E20: Les points de passage sont numérotés et précisément identifiés (lieu-dit ou coordonnées correctes)
E21: Les points de passage se retrouvent dans le tracé
E22: Les altitudes sont relevées correctement
E23: Les distances sont relevées correctement
E24: Les ponts et tunnels entre points du dispositif sont évités ou raisonnables
E25: Le plan horaire est réaliste (pauses régulières d'une durée adaptée, rythme de marche adapté)
D26: 3. Un concept de sécurité spécifique pour une randonnée est réalisé | G26: 2 | I26: =IFERROR(AVERAGEIF(H27:H34, "<>0"), "")
E27: Les informations générales de la randonnée sont présentées (responsables, de où à où, quand)
E28: Les informations générales concernant le groupe sont présentes (nombre, âges, expérience)
E29: Les risques majeurs sont identifiés (terrain, environnement, groupe), 3x3
E30: Pour les risques identifiés, des mesures adaptées sont prévues
E31: Une liste de matériel exhaustive est proposée
E32: Les critères d'annulation sont clairement définis, ainsi que l'alternative
E33: Les responsabilités sont définies au sein des responsables
E34: Une réaction en cas de crise est prévue, elle est réaliste et applicable
C35: 2. Réaliser une randonnée pour la branche éclais | F35: 1 | J35: =IFERROR(ROUND(IF(N35<=3, (N35-1)/2, 1 + (N35-3)*0.25),2),"") | N35: {=IFERROR(SUMPRODUCT(I36:I45,G36:G45)/SUMPRODUCT(--(I36:I45<>""),G36:G45),"")} | O35: =J35-N35 -> #VALUE!
D36: 1. Une adaptation aux éléments prévus dans le 3x3 a lieu tout au long de la randonnée | G36: 1 | I36: =IFERROR(AVERAGEIF(H37:H40, "<>0"), "")
E37: Attention axée sur le groupe tout au long de la marche
E38: Attention axée sur l'environnement au long de la marche (attentif aux dangers, annonce les dangers)
E39: Attention axée sur le terrain tout au long de la marche (se repère, emmène le groupe au bon endroit)
E40: Bonne communication entre les animateurices de la marche (transmission infos avant/arrière)
D41: 2. Les outils d'orientation et topographiques sont utilisés pour s'orienter correctement | G41: 1 | I41: =IFERROR(AVERAGEIF(H42:H45, "<>0"), "")
E42: Utiliser une boussole : orienter la carte, suivre un azimut, relever un azimut, le reporter sur la carte
E43: Se repérer sur une carte : estimer des distances et des dénivelés, report et relevée de coordonnées
E44: Choisir un point de non retour et une échappatoire pour "secourir" une patrouille
E45: Repérer et conseiller une patrouille à l'aide du tracé et du dispositif de marche
C46: 3. Effecuer des corrections de qualité et donner un retour sur une randonnée de la branche éclais | F46: 2 | J46: =IFERROR(ROUND(IF(N46<=3, (N46-1)/2, 1 + (N46-3)*0.25),2),"") | N46: {=IFERROR(SUMPRODUCT(I47:I67,G47:G67)/SUMPRODUCT(--(I47:I67<>""),G47:G67),"")} | O46: =J46-N46 -> #VALUE!
D47: 1. Les aspects importants d'une randonnée sont vérifiés | G47: 1 | I47: =IFERROR(AVERAGEIF(H48:H54, "<>0"), "")
E48: Correction sur la globalité du remplissage du canevas (responsable, n° de cartes, nom de la rando, etc)
E49: Correction de l'itinéraire (adapté aux participant.e.s, à la région et aux exigences J+S)
E50: Dispositif de marche cohérent avec le tracé (correspondance des points)
E51: Ponts et tunnels raisonnables sur le dispositif de marche (points de passage judicieux)
E52: Données relevées correctement (coordonnées, altitudes, distances)
E53: Plan horaire cohérent (pauses régulières et judicieusement placées, rythme de marche adapté au P)
E54: Lisibilité de la carte (traçé et informations lisibles, echelle adaptée)
D55: 2. Les aspects importants d'un concept de sécurité spécifique de randonnée sont vérifiés | G55: 2 | I55: =IFERROR(AVERAGEIF(H56:H61, "<>0"), "")
E56: Critères d'annulations présents
E57: Variante en cas de mauvais temps
E58: Identification des risques cohérente (saison, terrain et groupe)
E59: Mesures préventives pour répondre aux risques identifiés
E60: Réaction en cas de crise
E61: Responsabilités réparties au sein de la maîtrise
D62: 3. Des commentaires pertinents et de qualité sont transmis | G62: 1 | I62: =IFERROR(AVERAGEIF(H63:H67, "<>0"), "")
E63: Des éléments positifs sont relevés
E64: Les points principaux à améliorer sont relevés
E65: Les commentaires sont orientés solution
E66: Les commentaires sont clairs et concis
E67: Les commentaires sont constructifs
C68: 4. Planifier une activité de grande ampleur pour la branche éclais | F68: 2 | J68: =IFERROR(ROUND(IF(N68<=3, (N68-1)/2, 1 + (N68-3)*0.25),2),"") | N68: {=IFERROR(SUMPRODUCT(I69:I91,G69:G91)/SUMPRODUCT(--(I69:I91<>""),G69:G91),"")} | O68: =J68-N68 -> #VALUE!
D69: 1. Une déclaration pour une activité de grande ampleur est réalisée | G69: 1 | I69: =IFERROR(AVERAGEIF(H70:H75, "<>0"), "")
E70: Toutes les informations générales de l'activité sont saisies correctement
E71: Les consignes de réalisation de l'activité sont respectées
E72: Les descriptions et textes sont compréhensibles, explications claires
E73: Les objectifs de l'activité sont adaptés et réalistes
E74: Le système de rallye et clair, son fonctionnement est applicable
E75: Une variante appplicable est présente
D76: 2. Une déclaration pour un poste SC de 30 min est réalisée | G76: 1 | I76: =IFERROR(AVERAGEIF(H77:H84, "<>0"), "")
E77: Le sport est adapté aux participant.e.s
E78: Les consignes du sport sont claires et compréhensibles
E79: Courbe d'intensité cohérente
E80: Le canevas de déclaration est correctement rempli
E81: Originalité
E82: Liste de matériel cohérente
E83: Règles de sécurité présentes
E84: Variante prévue
D85: 3. Une déclaration pour un poste AC de 30 min est réalisée | G85: 1 | I85: =IFERROR(AVERAGEIF(H86:H91, "<>0"), "")
E86: L'activité proposée rentrent dans les domaines d'AC JS indiqués dans la décla.
E87: L'activité est adaptée aux participant.e.s
E88: Les consignes de l'activité sont claires et compréhensibles
E89: Le canevas de déclaration est correctement rempli
E90: Originalité
E91: Liste de matériel cohérente
C92: 5. Adapter et animer un sport de camp selon des contraintes externes | F92: 1 | J92: =IFERROR(ROUND(IF(N92<=3, (N92-1)/2, 1 + (N92-3)*0.25),2),"") | N92: {=IFERROR(SUMPRODUCT(I93:I106,G93:G106)/SUMPRODUCT(--(I93:I106<>""),G93:G106),"")} | O92: =J92-N92 -> #VALUE!
D93: 1. Un sport de camp est adapté en prenant en compte les contraintes externes | G93: 2 | I93: =IFERROR(AVERAGEIF(H94:H98, "<>0"), "")
E94: Réaction adéquate face aux contraintes
E95: Adaptation réaliste et fonctionnelle
E96: Il s'agit toujours d'un sport de camp
E97: Les exigences JS sont respectées
E98: Prise en compte de la courbe d'intensité
D99: 2. Un sport de camp est animé de manière adaptée | G99: 2 | I99: =IFERROR(AVERAGEIF(H100:H102, "<>0"), "")
E100: Attentif à la sécurité des participant.e.s
E101: Explications claires et compréhensibles
...

Sheet B - Organisation
C1: B - Organisation | K1: =_xlfn.CONCAT(Synthèse!C1, " // Cours ", Synthèse!H3) -> Kangourou / Toto Tutu // Cours RU - Chef de camp JS SdC/T | N1: Colonnes d'informations supplémentaires
N2: =COUNTBLANK(E11:E162) -> 74 | O2: =COUNTBLANK(H11:H163)-N2 -> 79 | P2: Nombre d'indicateurs vides
C3: =O6 | E3: Commentaire général | K3: Sera reporté dans la Synthèse | O3: =AVERAGEIF(H11:H163,"<>0") -> #DIV/0! | P3: Moyenne des indicateurs (tous confondus, sans passer par les pondérations)
O4: {=IFERROR(SUMPRODUCT(N11:N163,F11:F163)/SUMPRODUCT(--(N11:N163<>""),F11:F163),"")} | P4: Note de spère sans arrondi
O5: =C3-O4 -> #VALUE! | P5: Delta entre note sphèe arrondie et sans arrondi
F6: Pond. Obj. | G6: Pondérations | H6: Final | I6: Moy critères | J6: Moy objectif | O6: =IFERROR(ROUND(IF(O4<=3, (O4-1)/2, 1 + (O4-3)*0.25),2),"") | P6: Note de la sphère en % (3 = 100)
C7: Objectifs
D8: Critère | N8: objectif
E9: Indicateur | K9: Commentaire | N9: sans arrondi | O9: delta entre objectif arrondi et non arrondi
C11: 1. Réaliser un programme de camp | F11: 2 | J11: =IFERROR(ROUND(IF(N11<=3, (N11-1)/2, 1 + (N11-3)*0.25),2),"") | N11: {=IFERROR(SUMPRODUCT(I12:I22,G12:G22)/SUMPRODUCT(--(I12:I22<>""),G12:G22),"")} | O11: =J11-N11 -> #VALUE!
D12: 1. Le programme de camp est lisible | G12: 1 | I12: =IFERROR(AVERAGEIF(H13:H16, "<>0"), "")
E13: Les informations générales sont correctement rempli (lieu, dates, resp de camp, etc)
E14: Les informations J&S sont correctement remplies (Type de camp, Nb de jours JS, etc)
E15: Les objectifs d'unité sont compréhensibles et réaliste
E16: Les RUs se sont appropriés le canevas
D17: 2. Le programme de camp respecte les exigences J+S et MSdS | G17: 2 | I17: =IFERROR(AVERAGEIF(H18:H22, "<>0"), "")
E18: Les activités sont numérotées, le responsable de l'activité est indiqué
E19: Le programme de camp permet d'atteindre les objectifs de camp fixés
E20: Activités variées et équilibrées
E21: Les participant.e.s ont l'opportunités de prendre part à certaines décisions
E22: Les minimas J+S sont respectés (nb d'heures J+S) et permette l'équilibrage du programme
C23: 2. Planifier et administrer un camp à l'aide des outils à disposition | F23: 1 | J23: =IFERROR(ROUND(IF(N23<=3, (N23-1)/2, 1 + (N23-3)*0.25),2),"") | N23: {=IFERROR(SUMPRODUCT(I24:I51,G24:G51)/SUMPRODUCT(--(I24:I51<>""),G24:G51),"")} | O23: =J23-N23 -> #VALUE!
D24: 1. Les quantités figurant dans la liste de matériel de camp sont cohérentes | G24: 1 | I24: =IFERROR(AVERAGEIF(H25:H32, "<>0"), "")
E25: La liste est lisible, on comprend quel matériel est prévu, en quelles quantités
E26: Matériel de cuisine adapté au camp (nb part notamment)
E27: Matériel pour les activités cohérent avec les activités prévues durant le camp
E28: Matériel de technique de pionnier adapté (pour constructions, spécialités...)
E29: Tentes, toiles de tentes, bâches adapté (nb part, bivouac)
E30: Outillage
E31: Sécurité et infirmerie
E32: Sanitaire
D33: 2. L'implémentation du terrain de camp est présente | G33: 1 | I33: =IFERROR(AVERAGEIF(H34:H38, "<>0"), "")
E34: Bail à louer correctement rempli (section 1 à 3)
E35: Infrastructures essentielles présentes (tentes, réfectroire, cuisine, tente mat, latrines...)
E36: Placement adaté aux risques (pente, vent)
E37: Distances cohérentes et réalistes (sécurité)
E38: Le plan est utilisable sur le terrain (Echelle, légende, lisibilité, etc)
D39: 3. La circulaire de camp est rédigée de manière complète | G39: 1 | I39: =IFERROR(AVERAGEIF(H40:H45, "<>0"), "")
E40: Les informations du camp sont énoncées et adaptées (date, région, public, type de camp, etc)
E41: L'encadrement du camp est énoncé et adapté (personne de contact, J&S, etc)
E42: La modalité pour le paiement est formulé (Prix, moyen de paiement, délai, aide au paiement)
E43: Les informations sur la protection des données apparaisent (photo, protection des données, etc)
E44: Les informations demandé pour le questionnaire médical sont adaptées (allergies, AVS, etc)
E45: Le bulletin d'inscription est clair (date, signature, à qui et comment le rendre, délais, etc)
D46: 4. Les informations essentielles du camp sont transmises lors d'une présentation | G46: 1 | I46: =IFERROR(AVERAGEIF(H47:H51, "<>0"), "")
E47: Temps de parole réparti équitablement
E48: Support de présentation pertinent, qui sert le propos
E49: Les éléments essentiels d'un camp sont présents dans la présentation (selon instructions)
E50: Les réponses aux questions sont pertinentes et cohérentes
E51: La communication est adapté au public (posture, langage,etc)
C52: 3. Réaliser un concept de sécurité de camp complet | F52: 2 | J52: =IFERROR(ROUND(IF(N52<=3, (N52-1)/2, 1 + (N52-3)*0.25),2),"") | N52: {=IFERROR(SUMPRODUCT(I53:I80,G53:G80)/SUMPRODUCT(--(I53:I80<>""),G53:G80),"")} | O52: =J52-N52 -> #VALUE!
D53: 1. La gestion de crise pendant le camp est planifiée | G53: 2 | I53: =IFERROR(AVERAGEIF(H54:H57, "<>0"), "")
E54: Intégration du concept cantonal de gestion de crise dans la planification de camp
E55: Une marche à suivre en cas de situation de crise est planifiée de manière claire et complète
E56: Les numéros d'urgence / ressources médicales sont présents
E57: Les hopitaux et pharmacies de la région sont identifiés et indiqués
D58: 2. Les risques sont identifiés | G58: 1 | I58: =IFERROR(AVERAGEIF(H59:H62, "<>0"), "")
E59: Les risques généraux du camp sont identifiés
E60: Les risques spécifiques liés aux participants du camp sont identifiés
E61: Les risques spécifiques à la saison du camp sont identifiés
E62: Les risques spécifiques au terrain de camp sont identifiés
D63: 3. Les mesures préventives relatives aux risques sont identifiées | G63: 2 | I63: =IFERROR(AVERAGEIF(H64:H67, "<>0"), "")
E64: Risques généraux du camp
E65: Risques spécifiques liés aux participants du camp
E66: Risques spécifiques à la saison du camp
E67: Risques spécifiques au terrain de camp
D68: 4. Les informations générales du camp sont présentes | G68: 1 | I68: =IFERROR(AVERAGEIF(H69:H72, "<>0"), "")
E69: Le nom et le n° des encadrants pricipaux du camp sont intégrés au concept de sécurité
E70: La liste des activités nécessitant un concept de sécurité est complété selon le planning
E71: L'effectif de camp est cohérent (nb de cuistot, nb de responsable, etc)
E72: La localisation du camp est indiquée clairement (adresse, coordonnées, carte)
D73: 5. Les règles liées à la santé et l'hygiène sont intégrées au concept de sécurité | G73: 1 | I73: =IFERROR(AVERAGEIF(H74:H76, "<>0"), "")
E74: Un concept d'hygiène est présent (lié à la cuisine et aux maladies)
E75: Les règles liées à la sphère intime sont indiquées
E76: Le comportement avec la charte de camp est indiqué
D77: 6. La réaction en cas d'urgence est appliquée | G77: 1 | I77: =IFERROR(AVERAGEIF(H78:H80, "<>0"), "")
E78: Assure la réaction minimum en cas de situation de crise selon CdS (secours, cellule de crise, coach)
E79: Ne dégrade pas la situation (est capable de garder son calme)
E80: La réaction en cas de crise du CdS à été adaptée au regard de l'exercice de réaction en cas d'urgence
C81: 4. Planifier et diriger des maîtrises | F81: 1 | J81: =IFERROR(ROUND(IF(N81<=3, (N81-1)/2, 1 + (N81-3)*0.25),2),"") | N81: {=IFERROR(SUMPRODUCT(I82:I100,G82:G100)/SUMPRODUCT(--(I82:I100<>""),G82:G100),"")} | O81: =J81-N81 -> #VALUE!
D82: 1. Réalisation d'un ordre du jour et tenue d'un PV | G82: 1 | I82: =IFERROR(AVERAGEIF(H83:H88, "<>0"), "")
E83: OdJ, Tous les points à aborder dans la maîtrise sont présents (voir objectifs de la maîtrise)
E84: OdJ, Le canevas est rempli correctement (titre, date, liste de présence, sommaire, lisibilité)
E85: PV, Synthèse utile et claire des discussions pour chaque point de l'OdJ
E86: PV, Les décisions prises lors de la maitrise sont retranscrites, et facilement identifiables
E87: PV, Les éventuelles tâches a réaliser sont indiquées et réparties
E88: Lisibilité des documents (mise en page, ortographe, vocabulaire, formulations)
D89: 2. Une maîtrise est menée | G89: 1 | I89: =IFERROR(AVERAGEIF(H90:H94, "<>0"), "")
E90: L'ordre du jour est suivi, éventuellement adapté de manière cohérente
E91: Prend en compte les apports et remarques de sa maîtrise et répond aux éventuelles questions
E92: Acte de manière claire les décisions qui sont prises
E93: Respect du temps de parole de tous les membres de l'équipe
E94: Est attentif aux différentes personnalités de sa maîtrise et les prend en compte
D95: 3. Un retour à chaud constructif sur les acctivités des moniteurs est donné | G95: 1 | I95: =IFERROR(AVERAGEIF(H96:H100, "<>0"), "")
E96: Des éléments positifs sont relevés
E97: Les points principaux à améliorer sont relevés
E98: Le retour est constructif, le RU propose des pistes et/ou des directions à prendre
E99: Le retour permet au moniteur de se remettre en questions (formulation en questions)
E100: Le retour ne contient pas d'erreurs (respect des règles J+S et du MSdS)
C101: 5. Organiser sa maîtrise d'unité/de camp pour une collaboration efficace | F101: 1 | J101: =IFERROR(ROUND(IF(N101<=3, (N101-1)/2, 1 + (N101-3)*0.25),2),"") | N101: {=IFERROR(SUMPRODUCT(I102:I110,G102:G110)/SUMPRODUCT(--(I102:I110<>""),G102:G110),"")} | O101: =J101-N101 -> #VALUE!
...

Sheet C - Scoutisme
C1: C - Scoutisme | K1: =_xlfn.CONCAT(Synthèse!C1, " // Cours ", Synthèse!H3) -> Kangourou / Toto Tutu // Cours RU - Chef de camp JS SdC/T | N1: Colonnes d'informations supplémentaires
N2: =COUNTBLANK(E11:E147) -> 95 | O2: =COUNTBLANK(H11:H159)-N2 -> 54 | P2: Nombre d'indicateurs vides
C3: =O6 | E3: Commentaire général | K3: Sera reporté dans la Synthèse | O3: =AVERAGEIF(H11:H159,"<>0") -> #DIV/0! | P3: Moyenne des indicateurs (tous confondus, sans passer par les pondérations)
O4: {=IFERROR(SUMPRODUCT(N11:N159,F11:F159)/SUMPRODUCT(--(N11:N159<>""),F11:F159),"")} | P4: Note de spère sans arrondi
O5: =C3-O4 -> #VALUE! | P5: Delta entre note sphèe arrondie et sans arrondi
F6: Pond. Obj. | G6: Pondérations | H6: Final | I6: Moy critères | J6: Moy objectif | O6: =IFERROR(ROUND(IF(O4<=3, (O4-1)/2, 1 + (O4-3)*0.25),2),"") | P6: Note de la sphère en % (3 = 100)
C7: Objectifs
D8: Critère | N8: objectif
E9: Indicateur | K9: Commentaire | N9: sans arrondi | O9: delta entre objectif arrondi et non arrondi
C11: 1. Concevoir une journée d'activité de camp pour la branche concernée (activité de grande ampleur) | F11: 1 | J11: =IFERROR(ROUND(IF(N11<=3, (N11-1)/2, 1 + (N11-3)*0.25),2),"") | N11: {=IFERROR(SUMPRODUCT(I12:I19,G12:G19)/SUMPRODUCT(--(I12:I19<>""),G12:G19),"")} | O11: =J11-N11 -> #VALUE!
D12: 1. L'activité intègre la méthodologie scoute de la branche concernée | G12: 2 | I12: =IFERROR(AVERAGEIF(H13:H15, "<>0"), "")
E13: La ou les relations choisies sont pertinentes et en lien avec le descriptif de l'activité
E14: La ou les méthodes choisies sont pertinentes et en lien avec le descriptif de l'activité
E15: Le choix de méthodes et de relations permet d'atteindre l'objectif ou les objectifs de l'activité
D16: 2. Un thème est présent dans l'activité | G16: 1 | I16: =IFERROR(AVERAGEIF(H17:H19, "<>0"), "")
E17: Développement du thème, inscrit dans le canevas, durant les parties de l'activité
E18: Originalité dans le choix de développement du thème
E19: Le thème et son fil rouge prend en compte les besoins du groupe cible
C20: 2. Concevoir un programme de camp pour la branche concernée | F20: 2 | J20: =IFERROR(ROUND(IF(N20<=3, (N20-1)/2, 1 + (N20-3)*0.25),2),"") | N20: {=IFERROR(SUMPRODUCT(I21:I42,G21:G42)/SUMPRODUCT(--(I21:I42<>""),G21:G42),"")} | O20: =J20-N20 -> #VALUE!
D21: 1. Le programme respecte les besoins généraux des participant.e.s | G21: 1 | I21: =IFERROR(AVERAGEIF(H22:H25, "<>0"), "")
E22: Temps de sommeil adéquat (temps de préparation avant/après la nuit, adaptation en fonction du programme)
E23: Horaires d'activités cohérents (repas, corvé, transport, taille des blocs, temps de changement)
E24: Temps libres (Fréquence et répartition, plage suffisement longue pour développer l'autonomie, libre orienté)
E25: Hygiène respectée (fréquence, cohérence des placements)
D26: 2. Le programme propose un thème adapté au groupe cible | G26: 1 | I26: =IFERROR(AVERAGEIF(H27:H29, "<>0"), "")
E27: Originalité dans le choix de développement du thème
E28: Le thème et son fil rouge prend en compte les besoins du groupe cible
E29: Présence du thème le long du programme de camp
D30: 3. Le programme intègre les relations et les méthodes de manière équilibrée | G30: 2 | I30: =IFERROR(AVERAGEIF(H31:H33, "<>0"), "")
E31: Des phases d'apprentissage sont prévues afin de répondre aux objectifs de camp
E32: L'équilibre des méthodes et relations permet d'atteindre les objectifs de camp fixés
E33: L'équilibre d'AC, SC et AdA permet d'atteindre les objectifs de camps fixés
D34: 4. Le programme intègre les spécificités de la branche | G34: 1 | I34: =IFERROR(AVERAGEIF(H35:H42, "<>0"), "")
E35: Les étapes de la progression personnelle sont intégrées dans le programme
E36: Les spécialités de la progression personnelle sont intégrées dans le programme
E37: La méthode Symbolique et rituels est intégrée dans le programme
E38: La méthode du jeu et mouvement est intégrée dans le programme
E39: Des moments de reflexion personnelle sont intégrés dans le programme de camp (ex. AS)
E40: La méthode de la loi et la promesse est intégrée au camp
E41: Les participants ont l'occasion de prendre part à des projets et à des décisions
E42: La méthode de la vie en petit groupe est intégrée au camp
C43: 3. Concevoir un programme annuel pour la branche choisie | F43: 2 | J43: =IFERROR(ROUND(IF(N43<=3, (N43-1)/2, 1 + (N43-3)*0.25),2),"") | N43: {=IFERROR(SUMPRODUCT(I44:I64,G44:G64)/SUMPRODUCT(--(I44:I64<>""),G44:G64),"")} | O43: =J43-N43 -> #VALUE!
D44: 1. Les informations générales figurent sur le programme | G44: 1 | I44: =IFERROR(AVERAGEIF(H45:H47, "<>0"), "")
E45: Les informations générales sont correctement rempli
E46: Les objectifs d'unité sont compréhensibles et réaliste
E47: Les RUs se sont appropriés le canevas
D48: 2. La structure générale du programme est réfléchie et cohérente | G48: 1 | I48: =IFERROR(AVERAGEIF(H49:H51, "<>0"), "")
E49: Le choix des activités est adapté à la période et profite des opportunités de la saison
E50: La récurrence des séances décrite dans la gestion de maîtrise est respectée tout en prenant compte des weekends fériées
E51: Développement et présence du thème le long du programme annuel
D52: 3. Le programme intègre les relations et les méthodes de manière équilibrée | G52: 2 | I52: =IFERROR(AVERAGEIF(H53:H55, "<>0"), "")
E53: Des phases d'apprentissage sont prévues afin de répondre aux objectifs annuels
E54: Les méthodes sont variées au cours de l'année, tout en prenant compte les objectifs annuels
E55: Les relations sont variées au cours de l'année, tout en prenant compte des objectifs annuels
D56: 4. Le programme intègre les spécificités de la branche choisie | G56: 1 | I56: =IFERROR(AVERAGEIF(H57:H64, "<>0"), "")
E57: La progression personnelle est intégrée dans le programme (spécialités et étapes)
E58: La symbolique et les rituels sont présents au programme (cérémonie, passages, …)
E59: Des moments de reflexion personnelle sont intégrés dans le programme d'unités (ex. AS)
E60: La méthode du jeu et mouvement est exploitée durant les phases d'apprentissage
E61: L'utilisation de la méthode de la vie en pleine air est adapté à la saison
E62: La méthode loi et promesse est intégrée au programme annuel
E63: La méthode de la vie en petit groupe est intégrée dans le programme (activités de patrouille, piste en sizaine, …)
E64: Les participants ont l'occasion de prendre part à des projets et à des décisions (méthode apprendre en agissant)
E65: Les participants ont l'occasion de prendre part à la vie de la collectivité (méthode engagement pour la collectivité)

Sheet Critères éliminatoires
C1: Critères éliminatoires ! | E1: =_xlfn.CONCAT(Synthèse!C1, " // Cours JS") -> Kangourou / Toto Tutu // Cours JS
C3: OBLIGATOIRE : Justification de l'utilisation d'un critère éliminatoire | E3: Sera reporté dans la Synthèse
C7: Critères | D7: Utilisé | E7: Détails/Observations
C8: Ponctualité
C9: Le participant est en retard aux points de cours, malgré les avertissements (2 retards de plus de 5 min : tolérés mais avertissement. Au troisième retard : dernier avertissement). | D9: NON
C10: Présence
C11: Le participant a été absent à plus de 20% du cours (temps en jours). | D11: NON
C12: Le participant a loupé plus d'une heure de cours (non prévue). Il est possible de louper plus, mais seulement en avertissant la maîtrise en amont du cours, puis en acceptant et réalisant les mesures compensatoires exigées par la maîtrise). | D12: NON
C13: Le participant n'a pas participé au bivouac. | D13: NON
C14: Participation active/intérêt
C15: Après remarque de la maîtrise, le participant a continué à montrer du désintérêt, a décliné les opportunités de participer et n'a pas été attentif dans la globalité du cours. | D15: NON
C16: Après remarque de la maîtrise, le participant a continuer à faire preuve de mépris face aux différents contenus de cours, ne s'est pas impliqué ni investi dans sa formation. | D16: NON
C17: Pas de plagiat -> s’approprier son travail
C18: Le travail a été plagié (le travail peut s’inspirer de ressources ou d’expériences mais doit être adapté et réfléchi suivant les consignes. Un travail de rédaction et de réflexion doit être fourni. Le participant doit citer les ressources qu’il utilise directement dans les documents). | D18: NON
C19: Gestion de ses limites
C20: Le participant n'a pas remis ses rendus dans les délais impartis ou dans les délais prolongés en accord avec les formateurices (plus d'une heure de retard). | D20: NON
C21: Consommation de drogues durant le cours, peu importe le moment (aucun avertissement nécessaire). | D21: NON
C22: Fumée durant les point de cours malgré le 1er avertissement. | D22: NON
C23: Consommation abusive d'alcool ou d'alcool fort malgré un premier avertissement. La consommation se répercute sur le bon déroulement du cours du participant et altère ses capacités (Vomissements, perte d'autonomie, incapacité de se lever, de s'occuper de soi, agressivité, somnolence exagérée, points de cours non suivis). | D23: NON
C24: Respect et tolérance
C25: Le participant a risqué de mettre en danger le groupe ou lui-même par faute de reconnaissance de ses propres limites. | D25: NON
C26: Le participant n'est pas en état de suivre le cours de manière proactive après chaque nuit (1 seul avertissement). | D26: NON

Sheet Echelle
C1: Echelle
C3: Pour évaluer les indicateurs de la qualification, nous utilisons une échelle de couleur. Afin de simplifier l'utilisation chaque couleur est représentée par un nombre.
C5: Attention, chaque couleur a une signification, il ne s'agit pas d'une simple échelle de 1 a ....
D7: Case vide = non observé
C8: 1 | D8: Insuffisant, objectif non atteint, travail largement insuffisant. Attention, si plagiat, colorier en rouge pour repérer facilement le critère.
C9: 2 | D9: Objectif en voie d'aquisition, partiellement atteint. Le participant a compris la direction à prendre, mais le travail effectué ne permet pas d'atteindre l'objectif
C10: 3 | D10: Objectif atteint, la participante a effectué le "minimum" requis pour atteindre l'objectif
C11: 4 | D11: Objectif atteint avec aisance, le participant a montré de bonnes capacités et a réalisé un travail de qualité.
C12: 5 | D12: Travail excellent, au-delà des attentes du cours.

Sheet Attestation
J2: Faire l'impression depuis excel desktop (la version web bug)
J3: Imprimer sur du papier avec les logos préimprimés, excel fait de la m avec les logos
A4: Attestation de qualification
E7: Date | F7: Mercredi 3 avril 2024
E8: Lieux | F8: Les Bayards
A10: Nom | B10: =Synthèse!D5 -> Tutu | E10: Cours | F10: =Synthèse!H3 -> RU - Chef de camp JS SdC/T
A11: Prénom | B11: =Synthèse!D4 -> Toto | E11: N° | F11: =Synthèse!H4 -> PBS CH NE 221-26
A14: Qualifié en tant que :
A15: Moniteur JS Sport de camp/Trekking avec complément chef de camp
A18: Appréciation de la maîtrise
A20: Commentaire général
A21: =Synthèse!C8 -> 0
A25: Récapitulatif des points positifs | E25: Récapitulatif des points à améliorer
A26: =IF(ISBLANK(Synthèse!C13),"",Synthèse!C13) | E26: =IF(ISBLANK(Synthèse!G13),"",Synthèse!G13)
A27: =IF(ISBLANK(Synthèse!C14),"",Synthèse!C14) | E27: =IF(ISBLANK(Synthèse!G14),"",Synthèse!G14)
A28: =IF(ISBLANK(Synthèse!C15),"",Synthèse!C15) | E28: =IF(ISBLANK(Synthèse!G15),"",Synthèse!G15)
A31: Décision
A33: =IF(Synthèse!F24 = "Réussi", "Cours réussi", "Cours non réussi") -> Cours réussi | D33: Par la présente, la maîtrise atteste que le participant a accompli son cours et rempli les critères nécessaires pour obtenir sa reconnaissance de chef de camp JS Sport de camp/Trekking.
E36: Pour approbation : Le responsable de cours
E40: Bastien Nicoud

Sheet Listes
A1: Critères eliminatoires | F1: Texte réussi
A2: OUI | F2: Par la présente, la maîtrise atteste que le ou la participante a accompli son cours et rempli les critères nécessaires pour obtenir ça reconnaissance de chef de camp JS, Sport de camp trekking.
A3: NON
A5: Jocker
A6: AUCUN
A7: UTILISÉ

Sheet Objectifs MSdS
A1: Buts et objectifs du cours RU selon le MSdS | D1: Objectif reformulé pour la qualif
A4: Le cours donne aux participants la possibilité de réfléchir et de discuter les fondements du Mouvement Scout.
A5: 1.a | B5: ... disposent de connaissances approfondies des fondements du scoutisme et savent s’en servir pour garantir l'équilibre du programme scout. | D5: Utilisent les fondements du scoutisme pour garantir l'équilibre du programme de semestre Utilisent les fondements du scoutisme pour garantir l'équilibre du programme de camp
A6: 1.b | B6: ... disposent de connaissances approfondies des besoins des enfants et des jeunes de la branche Eclais. | D6: Prennent en compte les besoins des participants dans le programme de camp/semestre Menu de camp adapté aux besoins des enfants
A7: 1.c | B7: ... connaissent les objectifs de la branche Eclais tels que définis dans le Profil du scoutisme, ainsi que des moyens pour les atteindre.
A8: 1.d | B8: ... reconnaissent l'importance des moments calmes destinés à aborder la relation au spirituel et savent les intégrer dans le programme de la branche Eclais. | D8: Intégration d'AS dans le programme annuel et le programme de camp
A9: 1.e | B9: ... disposent de connaissances approfondies de la méthode scoute de la progression personnelle et savent l'intégrer de manière durable dans la branche Eclais. | D9: Intègrent les méthodes scoutes et la progression personnelle dans un programme de semestre Intègrent les méthodes scoutes et la progression personnelle dans un programme de camp
A10: 1.f | B10: ... connaissent les chances et les défis liés à l'intégration dans le scoutisme de personnes de culture différente.
A12: Le cours forme les participants à devenir des responsables d’unité ou de branche au sein d’une maîtrise.
A13: 2.a | B13: ... connaissent leur fonction ainsi que leurs droits et devoirs en tant que responsables d'unité ou de branche au sein de la branche Eclais.
A14: 2.b | B14: ... savent comment ils peuvent organiser leur unité ou leur branche (particulièrement comment assurer l’encadrement des responsables de patrouille) et connaissent des aspects de la planification à long terme.
A15: 2.c | B15: ... sont capables de montrer de l'assurance et représenter des intérêts.
A16: 2.d | B16: ... connaissent le concept cantonal de réaction en cas de crise et le rôle qu'ils y jouent. | D16: Intègrent le concept cantonal de gestion de crise dans leur planification de camp
A17: 2.e | B17: ... connaissent des moyens pour soigner consciemment les contacts avec les parents. | D17: Réalisent une circulaire de camp complète
A18: 2.f | B18: ... sont capables de développer et de mettre en œuvre, avec leur maîtrise, des stratégies permettant de gérer des enfants et des jeunes à comportement difficile.
A19: 2.g | B19: ... sont conscients de la problématique des dépendances et connaissent des moyens de prévention dans le programme scout ainsi que des pistes pour gérer les substances addictives au sein de la maîtrise. | D19: Le concept de sécurité identifie les risques liés aux dépendances et consomation de substances addictives et prévoit des mesures préventives.
A20: 2.h | B20: ... connaissent leur responsabilité par rapport à la prévention des abus sexuels et connaissent des mesures préventives dans ce domaine.
A21: 2.i | B21: ... connaissent les différentes formes de violence (psychique et physique) auxquelles ils peuvent être confrontés dans leur quotidien scout ainsi que des possibilités pour les prévenir.
A23: Le cours forme les participants à devenir des responsables de camp conscients de leurs responsabilités.
A24: 3.a | B24: ... connaissent leur fonction ainsi que leurs droits et devoirs en tant que chefs de camp.
A25: 3.b | B25: ... sont capables d’appliquer le règlement de camp du MSdS dans la planification. | D25: Appliquent le règlement de camp MSdS dans la planification
A26: 3.c | B26: ... connaissent les fonctions et responsabilités du coach et du RG, en particulier dans le domaine de l'encadrement des camps.
A27: 3.d | B27: ... connaissent le déroulement de la planification des camps, disposent d'outils pour chacune des étapes et savent administrer des camps. | D27: Planifient et administrent un camp à l'aide des outils à disposition.
A28: 3.e | B28: ... sont capables de réaliser des programmes de camp pour la branche Eclais et connaissent différentes formes de camp. | D28: Réalisent un programme de camp éclais
A29: 3.f | B29: ... sont capables de réaliser un concept de sécurité complet pour un camp. | D29: Réalisent un concept de sécurité de camp
A30: 3.g | B30: ... savent quelles mesures prendre pour garantir la santé des participants et connaissent des moyens pour gérer les maladies en camp. | D30: Règles liées à la santé et l'hygiène dans le cds
A31: 3.h | B31: ... peuvent adapter des jeux connus et organiser d'importantes activités sportives. | D31: Planifient une activité de grande ampleur. Adaptent un sport de camp Correction d'une AC et SC
A32: 3.i | B32: ... disposent de connaissances approfondies en planification, réalisation et évaluation de randonnées pour la branche Eclais. | D32: Planifient une randonnée pour la branche éclais Réalisent une randonnée pour la branche éclais Correction d'une randonnée
A33: 3.j | B33: ... les participants connaissent des possibilités pour intégrer une activité de patrouille dans un programme de camp et pour l’encadrer en conséquence.
A35: Le cours rend les participants capables d’accompagner et d’encadrer des jeunes responsables adjoints.
A36: 4.a | B36: ... connaissent leur rôle de responsable d'une maîtrise et les conditions cadres nécessaires à une collaboration efficace au sein de l’équipe. | D36: Dirigent une séance de préparation de camp (temps de parole)
A37: 4.b | B37: ... sont capables de préparer et de diriger une réunion. | D37: Rédigent un PV de réunion
A38: 4.c | B38: ... savent comment ils peuvent encadrer et encourager la progression personnelle de chaque membre de la maîtrise.
A39: 4.d | B39: ... connaissent des possibilités de formation et de perfectionnement.
